pyneural/__init__.py
pyneural/brain.py
pyneural/neurons.py
pyneural/save_manager.py
pyneural-0.0.2.dist-info/METADATA
pyneural-0.0.2.dist-info/WHEEL
pyneural-0.0.2.dist-info/top_level.txt
pyneural-0.0.2.dist-info/RECORD
