Metadata-Version: 2.1
Name: pyneural
Version: 0.0.2
Summary: Library for brain modeling and machine learning in Python 3
Home-page: UNKNOWN
Author: Tim Crimmins
Author-email: tim.g.crimmins@gmail.com
License: MIT
Platform: UNKNOWN
Classifier: Development Status :: 2 - Pre-Alpha
Classifier: Topic :: Scientific/Engineering :: Artificial Intelligence
Classifier: Topic :: Scientific/Engineering :: Artificial Life
Classifier: Topic :: Scientific/Engineering :: Bio-Informatics
Classifier: Programming Language :: Python :: 3
